treecker/__init__.py
treecker/__main__.py
treecker/_version.py
treecker/default.conf
treecker/core/__init__.py
treecker/core/colors.py
treecker/core/contents.py
treecker/core/display.py
treecker/core/naming.py
treecker/core/snapshot.py
treecker/core/tree.py
treecker/main/__init__.py
treecker/main/commit.py
treecker/main/init.py
treecker/main/issues.py
treecker/main/status.py
treecker-1.3.0.dist-info/LICENSE.txt
treecker-1.3.0.dist-info/METADATA
treecker-1.3.0.dist-info/WHEEL
treecker-1.3.0.dist-info/entry_points.txt
treecker-1.3.0.dist-info/top_level.txt
treecker-1.3.0.dist-info/RECORD
