Metadata-Version: 2.1
Name: treecker
Version: 1.3.0
Summary: Package to check the integrity of a directory.
Author-email: Dunstan Becht <dunstan.becht@orange.fr>
Project-URL: Homepage, https://gitlab.com/dustils/treecker
Project-URL: Bug Tracker, https://gitlab.com/dustils/treecker/issues
Project-URL: Documentation, https://dustils.gitlab.io/treecker
Classifier: Programming Language :: Python :: 3
Classifier: License :: OSI Approved :: GNU General Public License v3 (GPLv3)
Classifier: Operating System :: OS Independent
Classifier: Topic :: Utilities
Classifier: Topic :: System :: Filesystems
Classifier: Intended Audience :: End Users/Desktop
Requires-Python: >=3.9
License-File: LICENSE.txt
Requires-Dist: Pillow (>=9.5.0)
Requires-Dist: PyPDF2 (>=3.0.0)
